<?xml version="1.0" encoding="utf-8"?>
<content>
	<LoaderMax name="pageLoader8" load="true">
	
	<SWFLoader name="image1" autoPlay="false" url="pages/assets/m05p08/image1.swf" />

	<MP3Loader name="sound1" autoPlay="false" url="pages/assets/m05p08/m05p08.mp3" />
	</LoaderMax>

<transcript sound="sound1"><![CDATA[Correct storage is fundamental to the hygienic operation of any food business. Failure to ensure satisfactory storage conditions will result in hazards.<br /><br />Dry food stores should be:<li>Cool;</li><li>Dry;</li><li>Well-lit and well ventilated</li><li>Pest-proof; and</li><li>Kept clean and tidy.</li>]]></transcript> 

	<page sound="sound1" clearTime="19.8">
	
	
		<activities>
			<activity>Image</activity>
			<activity>Bullets</activity>
			<activity>AddText</activity>
			<activity>Transcript</activity>
		</activities>
		
		

		<statement delay="0" x="50" y="130" width="500" height="50"><![CDATA[Correct storage is fundamental to the hygienic operation of any food business; failure to ensure satisfactory storage conditions will result in hazards.]]></statement>
		
		<statement delay="12" x="50" y="190" width="500" height="50"><![CDATA[<b><font color='#7446A2'>Dry food stores should be:</font></b>]]></statement>
		<bullet delay="13" x="80" y="235" width="500" height="50"><![CDATA[Cool]]></bullet>
		<bullet delay="14" x="80" y="280" width="500" height="50"><![CDATA[Dry]]></bullet>
		<bullet delay="15" x="80" y="325" width="500" height="50"><![CDATA[Well-lit]]></bullet>
		<bullet delay="16" x="80" y="370" width="500" height="50"><![CDATA[Well-ventilated]]></bullet>
		<bullet delay="17" x="80" y="415" width="500" height="50"><![CDATA[Pest-proof]]></bullet>
		<bullet delay="18" x="80" y="460" width="500" height="50"><![CDATA[Clean and tidy.]]></bullet>
		
		<placeImage x="622.75" y="130" stop="yes" name="image1">
			<moveImage delay="0" x="622.75" y="138" alpha="1" />
		</placeImage>
		
		
		
		
	</page>
	

	
</content>